setup.py
bin/schnueffel-salt-events
schnueffelsaltevents/__init__.py
schnueffelsaltevents/schnueffelstueck.py
schnueffelsaltevents.egg-info/PKG-INFO
schnueffelsaltevents.egg-info/SOURCES.txt
schnueffelsaltevents.egg-info/dependency_links.txt
schnueffelsaltevents.egg-info/not-zip-safe
schnueffelsaltevents.egg-info/top_level.txt