Metadata-Version: 1.0
Name: schnueffelsaltevents
Version: 0.44
Summary: Attaches to a salt-masters event bus and logs all events to a (remote) log collecter
Home-page: https://github.com/MrMarvin/schnueffelsaltevents
Author: Marvin Frick
Author-email: marvin.frick@sinnerschrader.com
License: BSD
Platform: UNKNOWN
